crowdcent_challenge/__init__.py
crowdcent_challenge/cli.py
crowdcent_challenge/client.py
crowdcent_challenge/py.typed
crowdcent_challenge/scoring.py
crowdcent_challenge-0.1.17.dist-info/METADATA
crowdcent_challenge-0.1.17.dist-info/WHEEL
crowdcent_challenge-0.1.17.dist-info/entry_points.txt
crowdcent_challenge-0.1.17.dist-info/licenses/LICENSE
crowdcent_challenge-0.1.17.dist-info/RECORD
