Metadata-Version: 2.4
Name: crowdcent-challenge
Version: 0.1.17
Summary: CrowdCent Challenge Python Client
Author-email: Jason Rosenfeld <jason@crowdcent.com>
License-File: LICENSE
Requires-Python: >=3.10
Requires-Dist: click>=8.1.8
Requires-Dist: narwhals>=1.41.0
Requires-Dist: numpy>=2.0.2
Requires-Dist: python-dotenv>=1.1.0
Requires-Dist: requests>=2.32.3
Requires-Dist: scipy>=1.11.0
Requires-Dist: tqdm>=4.66.0
